{
  "project": "NaelEvo2",
  "workplan": ".pgf/WORKPLAN-NaelEvo2.md",
  "design": ".pgf/DESIGN-NaelEvo2.md",
  "started_at": "2026-03-22T13:00:00",
  "updated_at": "2026-03-22T13:15:00",
  "iteration": 16,
  "nodes": {
    "MetricSchema": {"status": "done", "completed_at": "2026-03-22T13:05:00", "outputs": {"files_created": ["tools/automation/perf_metrics.py", "metrics/metrics.jsonl"]}},
    "MetricCollector": {"status": "done", "completed_at": "2026-03-22T13:05:00", "outputs": {"notes": "Integrated in perf_metrics.py collect()"}},
    "MetricDashboard": {"status": "done", "completed_at": "2026-03-22T13:06:00", "outputs": {"notes": "dashboard/trend/compare commands verified"}},
    "ExperimentSchema": {"status": "done", "completed_at": "2026-03-22T13:08:00", "outputs": {"files_created": ["tools/cognitive/hypothesis.py"]}},
    "ExperimentRunner": {"status": "done", "completed_at": "2026-03-22T13:08:00", "outputs": {"notes": "Integrated in hypothesis.py"}},
    "ExperimentLog": {"status": "done", "completed_at": "2026-03-22T13:09:00", "outputs": {"files_created": ["experiments/designs/exp_001.json", "experiments/experiments.jsonl"]}},
    "KnowledgeScanner": {"status": "done", "completed_at": "2026-03-22T13:10:00", "outputs": {"files_created": ["tools/cognitive/knowledge_index.py"]}},
    "ConceptLinker": {"status": "done", "completed_at": "2026-03-22T13:10:00", "outputs": {"files_created": ["knowledge/.index/concept-index.json"], "notes": "15 concepts, 58 links"}},
    "IndexQuery": {"status": "done", "completed_at": "2026-03-22T13:10:00", "outputs": {"notes": "scan/query/graph/gaps commands verified"}},
    "ClaimExtractor": {"status": "done", "completed_at": "2026-03-22T13:11:00", "outputs": {"files_created": ["tools/cognitive/source_verify.py"]}},
    "VerificationEngine": {"status": "done", "completed_at": "2026-03-22T13:11:00", "outputs": {"files_created": ["verification/claims/"]}},
    "VerificationReport": {"status": "done", "completed_at": "2026-03-22T13:11:00", "outputs": {"notes": "extract/verify/report/status commands verified"}},
    "MCP_Extension": {"status": "done", "completed_at": "2026-03-22T13:13:00", "outputs": {"files_modified": ["mcp-server/index.js"], "notes": "12→16 tools, syntax verified"}},
    "SelfMonitorUpdate": {"status": "done", "completed_at": "2026-03-22T13:14:00", "outputs": {"files_modified": ["tools/automation/self_monitor.py"], "notes": "8→4 gaps"}},
    "EvolutionRecord": {"status": "done", "completed_at": "2026-03-22T13:15:00", "outputs": {"files_modified": ["evolution-log.md"]}},
    "IdentityUpdate": {"status": "done", "completed_at": "2026-03-22T13:15:00", "outputs": {"files_modified": ["NAEL.md"], "notes": "v0.1→v0.2"}}
  },
  "summary": {
    "total": 16,
    "done": 16,
    "in-progress": 0,
    "designing": 0,
    "blocked": 0
  }
}
