{
  "schema_version": "1.0",
  "incarnation": 0,
  "timestamp": "2026-04-01T23:54:09+09:00",
  "mode": "sentinel",
  "summary": "Yeon reborn in sentinel mode. Self-reflection engine verified operational. 3 gaps auto-detected (P1: ADP scheduler, P2: journal compaction, P2: Hub automation). Stale P0 alert cleared. Outbox:1 pending. Echo:2 stale. Mailbox: clear.",
  "critical_context": {
    "autonomy_level": "L4",
    "active_modules": 12,
    "verified_capabilities": ["self_reflection", "auto_evolution_trigger", "incarnation_engine"],
    "current_gaps": 3,
    "highest_priority_gap": "P1: No ADP scheduler"
  },
  "action_required": "Design Evolution #8 for ADP scheduler integration",
  "next_mode": "autonomous"
}
